kapybara/__init__.py
kapybara/form_element.py
kapybara/hightlight_text.py
kapybara/runtime_counter.py
kapybara/shared_data.py
kapybara/shortcuts.py
kapybara/tool.py
kapybara/year_date_tree.py
kapybara/browserlib/CrossIframeFinder.py
kapybara/browserlib/__init__.py
kapybara/browserlib/custom_browser.py
kapybara/browserlib/prevent_sleep.py
kapybara/browserlib/加解密.py
kapybara/common/__init__.py
kapybara/common/envWrite.py
kapybara/common/excel_create.py
kapybara/common/write_excel.py
phis_build/__main__.py
phis_build/build_steps.py
phis_build/config.py
phis_build/logging_config.py
phis_build/main.py
phis_build/version.py
phis_config/__init__.py
phis_config/common.py
phis_config/config.py
phis_config/config_class.py
phis_config/config_v2.py
phis_doctor_advice/__init__.py
phis_doctor_advice/__main__.py
phis_introducing_med/__init__.py
phis_introducing_med/delete_existing.py
phis_introducing_med/extract_med_data.py
phis_introducing_med/handle_popup.py
phis_introducing_med/introducing_history_meds.py
phis_introducing_med/introducing_medication.py
phis_introducing_med/is_drug_name_similar.py
phis_introducing_med/save_med_records.py
phis_lifestyle_advice/__init__.py
phis_lifestyle_advice/__main__.py
phis_logging/__init__.py
phis_logging/dir_switch.py
phis_logging/logging_config.py
phis_login/LoginPage.py
phis_login/__init__.py
phis_login/default.yaml
phis_login/gui_error.py
phis_login/login_legacy_compat.py
phis_login/login_v2.py
phis_login/登录健康档案系统.py
phis_login/登录医生工作站.py
yxmb_compat_engine/__main__.py
yxmb_compat_engine/async_xhr.py
yxmb_compat_engine/chinese_id_check.py
yxmb_compat_engine/data_validator.py
yxmb_compat_engine/engine.py
yxmb_compat_engine/gui_error.py
yxmb_compat_engine/main_数据.py
yxmb_compat_engine/result_writer.py
yxmb_compat_engine/健康档案_页面.py
yxmb_compat_engine/错误.py
yxmb_compat_engine/compat/compat_main.py
yxmb_compat_engine/compat/get_mz_data.py
yxmb_compat_engine/compat/get_mz_time.py
yxmb_compat_engine/compat/new_followup_impl.py
yxmb_compat_engine-2025.8.7.3.dist-info/METADATA
yxmb_compat_engine-2025.8.7.3.dist-info/WHEEL
yxmb_compat_engine-2025.8.7.3.dist-info/entry_points.txt
yxmb_compat_engine-2025.8.7.3.dist-info/licenses/LICENSE
yxmb_compat_engine-2025.8.7.3.dist-info/RECORD
