Metadata-Version: 2.4
Name: yxmb-compat-engine
Version: 2025.8.7.3
Summary: 宇信慢病兼容版引擎
License-File: LICENSE
Requires-Python: >=3.12
Requires-Dist: dask>=2025.7.0
Requires-Dist: ddddocr>=1.5.6
Requires-Dist: ocr-hooks>=2025.8.4.1
Requires-Dist: openpyxl>=3.1.5
Requires-Dist: pandas>=2.3.1
Requires-Dist: pydantic>=2.11.7
Requires-Dist: pyinstaller>=6.15.0
Requires-Dist: selenium>=4.34.2
Requires-Dist: tqdm>=4.67.1
